{
        "mapdata" : [

"f0", "f0", "f0", "f0", "f0", "f0", "f0", "f0", "f0", "f0", "f0", "f0", "f0", "f0", "f0", "f0", "f0", "f0", "f0", "f0", "f0", "f0", "f0", "f0", "f0", "f0", "f0", "f0", "f0", "f0", "f0", 
"f0", "f0", "f0", "f0", "f0", "f0", "f0", "f0", "f0", "f0", "f0", "f0", "f0", "f0", "f0", "f0", "f0", "f0", "f0", "f0", "f0", "f0", "f0", "f0", "f0", "f0", "f0", "f0", "f0", "f0", "f0", 
"f0", "f0", "f0", "f0", "f0", "f0", "f0", "f0", "f0", "f0", "f0", "f0", "f0", "wq", "wm", "wm", "wm", "wm", "wm", "wr", "f0", "f0", "f0", "f0", "f0", "f0", "f0", "f0", "f0", "f0", "f0",
"f0", "f0", "f0", "f0", "f0", "f0", "f0", "f0", "f0", "f0", "wq", "wm", "wm", "wp", "wj", "fi", "fi", "fi", "wj", "wn", "wm", "wm", "wr", "f0", "f0", "f0", "f0", "f0", "f0", "f0", "f0",
"f0", "f0", "f0", "f0", "f0", "f0", "f0", "f0", "f0", "wq", "wp", "wj", "wi", "wj", "wi", "fi", "fi", "fi", "wi", "wj", "wi", "wj", "wn", "wr", "f0", "f0", "f0", "f0", "f0", "f0", "f0",
"f0", "f0", "f0", "f0", "f0", "f0", "f0", "f0", "wq", "wp", "wj", "wi", "wj", "wi", "fi", "fi", "fi", "fi", "fi", "wi", "wj", "wi", "wj", "wn", "wr", "f0", "f0", "f0", "f0", "f0", "f0",
"f0", "f0", "f0", "f0", "f0", "f0", "f0", "wq", "wp", "wj", "wi", "fi", "fi", "fi", "fi", "fi", "fi", "fi", "fi", "fi", "fi", "fi", "wi", "wj", "wn", "wr", "f0", "f0", "f0", "f0", "f0",
"f0", "f0", "f0", "f0", "f0", "f0", "f0", "wo", "wj", "wi", "fi", "fi", "fi", "fi", "fi", "fi", "fi", "fi", "fi", "fi", "fi", "fi", "fi", "wi", "wj", "wo", "f0", "f0", "f0", "f0", "f0",
"f0", "f0", "f0", "f0", "f0", "f0", "wq", "wp", "wi", "fi", "fi", "fi", "fi", "fi", "fi", "fi", "fi", "fi", "fi", "fi", "fi", "fi", "fi", "fi", "wi", "wn", "wr", "f0", "f0", "f0", "f0",
"f0", "f0", "f0", "f0", "f0", "f0", "wo", "wi", "fi", "fi", "fi", "fi", "fi", "fi", "fi", "fi", "fi", "fi", "fi", "fi", "fi", "fi", "fi", "fi", "fi", "wi", "wo", "f0", "f0", "f0", "f0",
"f0", "f0", "f0", "f0", "f0", "f0", "wo", "wj", "fi", "fi", "fi", "fi", "fi", "fi", "fi", "fi", "fi", "fi", "fi", "fi", "fi", "fi", "fi", "fi", "fi", "wj", "wo", "f0", "f0", "f0", "f0", 
"f0", "f0", "f0", "f0", "f0", "f0", "wo", "fi", "fi", "fi", "fi", "fi", "fi", "fi", "fi", "fi", "fi", "fi", "fi", "fi", "fi", "fi", "fi", "fi", "fi", "fi", "wo", "f0", "f0", "f0", "f0",
"f0", "f0", "f0", "f0", "f0", "f0", "wo", "fi", "fi", "fi", "fi", "fi", "fi", "fi", "fi", "fi", "fi", "fi", "fi", "fi", "fi", "fi", "fi", "fi", "fi", "fi", "wo", "f0", "f0", "f0", "f0",
"f0", "f0", "f0", "f0", "f0", "f0", "wn", "wr", "fi", "fi", "fi", "wm", "wm", "wm", "wm", "wm", "wm", "wm", "wm", "wm", "wm", "wm", "fi", "fi", "fi", "wq", "wp", "f0", "f0", "f0", "f0",
"f0", "f0", "f0", "f0", "f0", "f0", "wj", "wo", "fi", "fi", "fi", "wj", "wi", "wj", "wi", "wj", "wi", "wj", "wi", "wj", "wi", "wj", "fi", "fi", "fi", "wo", "wi", "f0", "f0", "f0", "f0",
"f0", "f0", "f0", "f0", "f0", "f0", "wi", "wn", "wr", "fi", "fi", "fi", "fi", "fi", "fi", "fi", "fi", "fi", "fi", "fi", "fi", "fi", "fi", "fi", "wq", "wp", "wj", "f0", "f0", "f0", "f0",
"f0", "f0", "f0", "f0", "f0", "f0", "wj", "wi", "wn", "wr", "fi", "fi", "fi", "fi", "fi", "fi", "fi", "fi", "fi", "fi", "fi", "fi", "fi", "wq", "wp", "wj", "wi", "f0", "f0", "f0", "f0",
"f0", "f0", "f0", "f0", "f0", "f0", "wi", "wj", "wj", "wn", "wr", "fi", "fi", "fi", "fi", "fi", "fi", "fi", "fi", "fi", "fi", "fi", "wq", "wp", "wj", "wi", "wj", "f0", "f0", "f0", "f0",
"f0", "f0", "f0", "f0", "f0", "f0", "wj", "wi", "wj", "wi", "wn", "wm", "wm", "wr", "fi", "fi", "fi", "fi", "fe3","wq", "wm", "wm", "wp", "wi", "wi", "wj", "wi", "f0", "f0", "f0", "f0",
"f0", "f0", "f0", "f0", "f0", "f0", "wi", "wj", "wi", "wj", "wj", "wi", "wj", "wn", "wm", "wm", "wm", "wm", "wm", "wp", "wj", "wi", "wj", "wi", "wj", "wi", "wj", "f0", "f0", "f0", "f0",
"f0", "f0", "f0", "f0", "f0", "f0", "wj", "wi", "wj", "wi", "wj", "wi", "wj", "wi", "wj", "wi", "wi", "wj", "wi", "wj", "wi", "wj", "wi", "wj", "wi", "wj", "wi", "f0", "f0", "f0", "f0", 
"f0", "f0", "f0", "f0", "f0", "f0", "wi", "wj", "wi", "wj", "wi", "wj", "wi", "wj", "wi", "wi", "wj", "wi", "wj", "wi", "wj", "wi", "wj", "wi", "wj", "wi", "wj", "f0", "f0", "f0", "f0"

        ] ,
        "mapdims" : { "x":31,"y":22 },
	    "bosslocation": { "x":15,"y":3 },
	    "bosstype": 1
}
